doodle_translate-0.2.4.data/scripts/google-translate
doodle_translate-0.2.4.dist-info/DESCRIPTION.rst
doodle_translate-0.2.4.dist-info/METADATA
doodle_translate-0.2.4.dist-info/RECORD
doodle_translate-0.2.4.dist-info/WHEEL
doodle_translate-0.2.4.dist-info/metadata.json
doodle_translate-0.2.4.dist-info/top_level.txt
google_translate/__init__.py
google_translate/cache.py
google_translate/options.py
google_translate/selectors.py
google_translate/tk_generator.py
google_translate/translator.py
google_translate/utils.py
google_translate/version.py
google_translate/data/languages
