Metadata-Version: 1.1
Name: doodle-translate
Version: 0.2.4
Summary: Small Python library to translate text for free using the Google translate.
Home-page: https://github.com/MrS0m30n3/google-translate
Author: Sotiris Papadopoulos
Author-email: ytubedlg@gmail.com
License: Unlicense
Keywords: google translate language free
Platform: UNKNOWN
Classifier: Intended Audience :: Developers
Classifier: License :: Public Domain
Classifier: Operating System :: OS Independent
Classifier: Programming Language :: Python
Classifier: Topic :: Software Development :: Build Tools
Classifier: Topic :: Software Development :: Libraries :: Python Modules
